{
  "updated_at": "2026-04-12 19:48",
  "message": "рҹҢӨпёҸ Weer vir vandag\n\nрҹҢ… Son op: 07:05\nрҹҢҮ Son sak: 18:27\n\nрҹҢЎпёҸ Min: 14.1В°C\nрҹҢЎпёҸ Max: 26.2В°C\n\nрҹҢ§пёҸ ReГ«n kans: 0%\nрҹҢ§пёҸ ReГ«n totaal: 0.0 mm\n\nвҸұпёҸ ReГ«n kans volgende 30 min: 0% (0.00 mm)\n\nрҹ’Ё Wind: 22.5 km/h S\nвҳҖпёҸ UV Index: 6.20",
  "next30_rain_prob": 0,
  "next30_rain_mm": 0.0,
  "week": [
    {
      "date": "2026-04-12",
      "min": 14.1,
      "max": 26.2,
      "rain_prob": 0,
      "rain_mm": 0.0,
      "wind_kmh": 22.5,
      "wind_dir": "S",
      "uv": 6.2,
      "sunrise": "07:05",
      "sunset": "18:27"
    },
    {
      "date": "2026-04-13",
      "min": 13.8,
      "max": 29.4,
      "rain_prob": 0,
      "rain_mm": 0.0,
      "wind_kmh": 8.3,
      "wind_dir": "S",
      "uv": 6.1,
      "sunrise": "07:06",
      "sunset": "18:26"
    },
    {
      "date": "2026-04-14",
      "min": 14.5,
      "max": 22.6,
      "rain_prob": 28,
      "rain_mm": 0.0,
      "wind_kmh": 21.8,
      "wind_dir": "NW",
      "uv": 6.05,
      "sunrise": "07:06",
      "sunset": "18:24"
    },
    {
      "date": "2026-04-15",
      "min": 13.0,
      "max": 21.6,
      "rain_prob": 50,
      "rain_mm": 0.4,
      "wind_kmh": 17.1,
      "wind_dir": "SW",
      "uv": 5.45,
      "sunrise": "07:07",
      "sunset": "18:23"
    },
    {
      "date": "2026-04-16",
      "min": 9.0,
      "max": 23.0,
      "rain_prob": 0,
      "rain_mm": 0.0,
      "wind_kmh": 19.5,
      "wind_dir": "S",
      "uv": 5.15,
      "sunrise": "07:08",
      "sunset": "18:22"
    },
    {
      "date": "2026-04-17",
      "min": 10.6,
      "max": 18.0,
      "rain_prob": 32,
      "rain_mm": 1.8,
      "wind_kmh": 32.7,
      "wind_dir": "NW",
      "uv": 5.75,
      "sunrise": "07:08",
      "sunset": "18:21"
    },
    {
      "date": "2026-04-18",
      "min": 12.8,
      "max": 16.9,
      "rain_prob": 35,
      "rain_mm": 1.5,
      "wind_kmh": 27.0,
      "wind_dir": "NW",
      "uv": 3.5,
      "sunrise": "07:09",
      "sunset": "18:20"
    }
  ]
}