{
  "updated_at": "2026-05-14 03:32",
  "message": "рҹҢӨпёҸ Weer vir vandag\n\nрҹҢ… Son op: 07:28\nрҹҢҮ Son sak: 17:54\n\nрҹҢЎпёҸ Min: 8.3В°C\nрҹҢЎпёҸ Max: 19.0В°C\n\nрҹҢ§пёҸ ReГ«n kans: 0%\nрҹҢ§пёҸ ReГ«n totaal: 0.0 mm\n\nвҸұпёҸ ReГ«n kans volgende 30 min: 0% (0.00 mm)\n\nрҹ’Ё Wind: 10.4 km/h S\nвҳҖпёҸ UV Index: 4.35",
  "next30_rain_prob": 0,
  "next30_rain_mm": 0.0,
  "week": [
    {
      "date": "2026-05-14",
      "min": 8.3,
      "max": 19.0,
      "rain_prob": 0,
      "rain_mm": 0.0,
      "wind_kmh": 10.4,
      "wind_dir": "S",
      "uv": 4.35,
      "sunrise": "07:28",
      "sunset": "17:54"
    },
    {
      "date": "2026-05-15",
      "min": 11.6,
      "max": 20.5,
      "rain_prob": 0,
      "rain_mm": 0.0,
      "wind_kmh": 15.4,
      "wind_dir": "S",
      "uv": 4.4,
      "sunrise": "07:29",
      "sunset": "17:54"
    },
    {
      "date": "2026-05-16",
      "min": 9.5,
      "max": 24.0,
      "rain_prob": 0,
      "rain_mm": 0.0,
      "wind_kmh": 10.2,
      "wind_dir": "SE",
      "uv": 4.4,
      "sunrise": "07:29",
      "sunset": "17:53"
    },
    {
      "date": "2026-05-17",
      "min": 11.1,
      "max": 24.8,
      "rain_prob": 0,
      "rain_mm": 0.0,
      "wind_kmh": 13.5,
      "wind_dir": "SE",
      "uv": 4.35,
      "sunrise": "07:30",
      "sunset": "17:52"
    },
    {
      "date": "2026-05-18",
      "min": 13.9,
      "max": 22.7,
      "rain_prob": 2,
      "rain_mm": 0.0,
      "wind_kmh": 22.4,
      "wind_dir": "SE",
      "uv": 4.2,
      "sunrise": "07:31",
      "sunset": "17:52"
    },
    {
      "date": "2026-05-19",
      "min": 14.4,
      "max": 22.5,
      "rain_prob": 4,
      "rain_mm": 0.0,
      "wind_kmh": 21.9,
      "wind_dir": "SE",
      "uv": 4.0,
      "sunrise": "07:31",
      "sunset": "17:51"
    },
    {
      "date": "2026-05-20",
      "min": 15.5,
      "max": 24.0,
      "rain_prob": 4,
      "rain_mm": 0.0,
      "wind_kmh": 8.4,
      "wind_dir": "S",
      "uv": 4.0,
      "sunrise": "07:32",
      "sunset": "17:50"
    }
  ]
}