{
  "updated_at": "2026-03-28 12:17",
  "message": "рҹҢӨпёҸ Weer vir vandag\n\nрҹҢ… Son op: 06:54\nрҹҢҮ Son sak: 18:46\n\nрҹҢЎпёҸ Min: 15.6В°C\nрҹҢЎпёҸ Max: 25.9В°C\n\nрҹҢ§пёҸ ReГ«n kans: 30%\nрҹҢ§пёҸ ReГ«n totaal: 0.5 mm\n\nвҸұпёҸ ReГ«n kans volgende 30 min: 8% (0.00 mm)\n\nрҹ’Ё Wind: 18.7 km/h SW\nвҳҖпёҸ UV Index: 7.00",
  "next30_rain_prob": 8,
  "next30_rain_mm": 0.0,
  "week": [
    {
      "date": "2026-03-28",
      "min": 15.6,
      "max": 25.9,
      "rain_prob": 30,
      "rain_mm": 0.5,
      "wind_kmh": 18.7,
      "wind_dir": "SW",
      "uv": 7.0,
      "sunrise": "06:54",
      "sunset": "18:46"
    },
    {
      "date": "2026-03-29",
      "min": 12.0,
      "max": 25.4,
      "rain_prob": 0,
      "rain_mm": 0.0,
      "wind_kmh": 19.6,
      "wind_dir": "S",
      "uv": 7.0,
      "sunrise": "06:55",
      "sunset": "18:45"
    },
    {
      "date": "2026-03-30",
      "min": 12.2,
      "max": 26.5,
      "rain_prob": 0,
      "rain_mm": 0.0,
      "wind_kmh": 22.3,
      "wind_dir": "S",
      "uv": 6.95,
      "sunrise": "06:56",
      "sunset": "18:43"
    },
    {
      "date": "2026-03-31",
      "min": 12.7,
      "max": 29.7,
      "rain_prob": 0,
      "rain_mm": 0.0,
      "wind_kmh": 17.4,
      "wind_dir": "SW",
      "uv": 6.9,
      "sunrise": "06:56",
      "sunset": "18:42"
    },
    {
      "date": "2026-04-01",
      "min": 13.8,
      "max": 31.1,
      "rain_prob": 2,
      "rain_mm": 0.0,
      "wind_kmh": 18.1,
      "wind_dir": "S",
      "uv": 6.8,
      "sunrise": "06:57",
      "sunset": "18:41"
    },
    {
      "date": "2026-04-02",
      "min": 18.9,
      "max": 34.6,
      "rain_prob": 9,
      "rain_mm": 3.3,
      "wind_kmh": 23.7,
      "wind_dir": "NW",
      "uv": 4.45,
      "sunrise": "06:58",
      "sunset": "18:39"
    },
    {
      "date": "2026-04-03",
      "min": 16.6,
      "max": 26.3,
      "rain_prob": 15,
      "rain_mm": 0.0,
      "wind_kmh": 21.6,
      "wind_dir": "S",
      "uv": 6.45,
      "sunrise": "06:58",
      "sunset": "18:38"
    }
  ]
}