{
  "updated_at": "2026-04-29 05:59",
  "message": "рҹҢӨпёҸ Weer vir vandag\n\nрҹҢ… Son op: 07:17\nрҹҢҮ Son sak: 18:07\n\nрҹҢЎпёҸ Min: 7.7В°C\nрҹҢЎпёҸ Max: 21.4В°C\n\nрҹҢ§пёҸ ReГ«n kans: 0%\nрҹҢ§пёҸ ReГ«n totaal: 0.0 mm\n\nвҸұпёҸ ReГ«n kans volgende 30 min: 0% (0.00 mm)\n\nрҹ’Ё Wind: 18.7 km/h SE\nвҳҖпёҸ UV Index: 5.20",
  "next30_rain_prob": 0,
  "next30_rain_mm": 0.0,
  "week": [
    {
      "date": "2026-04-29",
      "min": 7.7,
      "max": 21.4,
      "rain_prob": 0,
      "rain_mm": 0.0,
      "wind_kmh": 18.7,
      "wind_dir": "SE",
      "uv": 5.2,
      "sunrise": "07:17",
      "sunset": "18:07"
    },
    {
      "date": "2026-04-30",
      "min": 8.8,
      "max": 20.9,
      "rain_prob": 0,
      "rain_mm": 0.0,
      "wind_kmh": 17.0,
      "wind_dir": "S",
      "uv": 5.15,
      "sunrise": "07:18",
      "sunset": "18:06"
    },
    {
      "date": "2026-05-01",
      "min": 8.1,
      "max": 17.5,
      "rain_prob": 2,
      "rain_mm": 0.0,
      "wind_kmh": 20.0,
      "wind_dir": "NW",
      "uv": 4.4,
      "sunrise": "07:18",
      "sunset": "18:05"
    },
    {
      "date": "2026-05-02",
      "min": 11.4,
      "max": 21.9,
      "rain_prob": 10,
      "rain_mm": 0.0,
      "wind_kmh": 13.3,
      "wind_dir": "N",
      "uv": 4.85,
      "sunrise": "07:19",
      "sunset": "18:04"
    },
    {
      "date": "2026-05-03",
      "min": 11.4,
      "max": 21.5,
      "rain_prob": 14,
      "rain_mm": 0.0,
      "wind_kmh": 18.6,
      "wind_dir": "NW",
      "uv": 4.95,
      "sunrise": "07:20",
      "sunset": "18:03"
    },
    {
      "date": "2026-05-04",
      "min": 11.6,
      "max": 18.5,
      "rain_prob": 69,
      "rain_mm": 7.2,
      "wind_kmh": 19.0,
      "wind_dir": "NW",
      "uv": 1.55,
      "sunrise": "07:20",
      "sunset": "18:02"
    },
    {
      "date": "2026-05-05",
      "min": 10.4,
      "max": 15.9,
      "rain_prob": 61,
      "rain_mm": 18.0,
      "wind_kmh": 18.8,
      "wind_dir": "NW",
      "uv": 4.0,
      "sunrise": "07:21",
      "sunset": "18:02"
    }
  ]
}